arboretum/__init__.py
arboretum/ansible/__init__.py
arboretum/ansible/checks/__init__.py
arboretum/ansible/evidences/__init__.py
arboretum/ansible/fetchers/__init__.py
arboretum/ansible/reports/__init__.py
arboretum/ansible/templates/default.md.tmpl
arboretum/auditree/__init__.py
arboretum/auditree/checks/__init__.py
arboretum/auditree/checks/test_abandoned_evidence.py
arboretum/auditree/checks/test_compliance_config.py
arboretum/auditree/checks/test_empty_evidence.py
arboretum/auditree/checks/test_filepath_commits.py
arboretum/auditree/checks/test_locker_commit_integrity.py
arboretum/auditree/checks/test_locker_large_files.py
arboretum/auditree/checks/test_locker_repo_integrity.py
arboretum/auditree/checks/test_python_packages.py
arboretum/auditree/checks/test_repo_branch_commits.py
arboretum/auditree/evidences/__init__.py
arboretum/auditree/evidences/python_package_release.py
arboretum/auditree/evidences/repo_branch_protection.py
arboretum/auditree/evidences/repo_commit.py
arboretum/auditree/evidences/repo_metadata.py
arboretum/auditree/fetchers/__init__.py
arboretum/auditree/fetchers/fetch_abandoned_evidence.py
arboretum/auditree/fetchers/fetch_compliance_config.py
arboretum/auditree/fetchers/fetch_python_packages.py
arboretum/auditree/fetchers/github/__init__.py
arboretum/auditree/fetchers/github/fetch_branch_protection.py
arboretum/auditree/fetchers/github/fetch_filepath_commits.py
arboretum/auditree/fetchers/github/fetch_recent_commits.py
arboretum/auditree/fetchers/github/fetch_repo_metadata.py
arboretum/auditree/reports/__init__.py
arboretum/auditree/templates/default.md.tmpl
arboretum/auditree/templates/reports/auditree/abandoned_evidence.md.tmpl
arboretum/auditree/templates/reports/auditree/compliance_config.md.tmpl
arboretum/auditree/templates/reports/auditree/filepath_new_commits.md.tmpl
arboretum/auditree/templates/reports/auditree/locker_commit_integrity.md.tmpl
arboretum/auditree/templates/reports/auditree/locker_repo_integrity.md.tmpl
auditree_arboretum-0.17.1.dist-info/LICENSE
auditree_arboretum-0.17.1.dist-info/METADATA
auditree_arboretum-0.17.1.dist-info/WHEEL
auditree_arboretum-0.17.1.dist-info/top_level.txt
auditree_arboretum-0.17.1.dist-info/RECORD
