Metadata-Version: 2.1
Name: auditree-arboretum
Version: 0.17.1
Summary: The Auditree common fetchers, checks and harvest reports library
Home-page: https://auditree.github.io/
Author: Auditree Security and Compliance
Author-email: al.finkelstein@ibm.com
License: Apache License 2.0
Classifier: Programming Language :: Python :: 3.6
Classifier: Programming Language :: Python :: 3.7
Classifier: Programming Language :: Python :: 3.8
Classifier: Programming Language :: Python :: 3.9
Classifier: License :: OSI Approved :: Apache Software License
Classifier: Operating System :: MacOS :: MacOS X
Classifier: Operating System :: POSIX :: Linux
License-File: LICENSE
Requires-Dist: auditree-framework >=1.2.3
Requires-Dist: auditree-harvest >=1.0.0
Requires-Dist: pyyaml >=5.4.1
Requires-Dist: defusedxml >=0.7.1
Requires-Dist: parameterized >=0.8.1
Provides-Extra: dev
Requires-Dist: pytest >=5.4.3 ; extra == 'dev'
Requires-Dist: pytest-cov >=2.10.0 ; extra == 'dev'
Requires-Dist: bandit >=1.5.0 ; extra == 'dev'
Requires-Dist: pre-commit >=2.4.0 ; extra == 'dev'
Requires-Dist: Sphinx >=1.7.2 ; extra == 'dev'
Requires-Dist: setuptools ; extra == 'dev'
Requires-Dist: wheel ; extra == 'dev'
Requires-Dist: twine ; extra == 'dev'
